invenio_oarepo_files_rest/__init__.py
invenio_oarepo_files_rest/buckets.py
invenio_oarepo_files_rest/cli.py
invenio_oarepo_files_rest/config.py
invenio_oarepo_files_rest/ext.py
invenio_oarepo_files_rest/locations.py
invenio_oarepo_files_rest/proxies.py
invenio_oarepo_files_rest/version.py
invenio_oarepo_files_rest-1.0.4.dist-info/AUTHORS.rst
invenio_oarepo_files_rest-1.0.4.dist-info/LICENSE
invenio_oarepo_files_rest-1.0.4.dist-info/METADATA
invenio_oarepo_files_rest-1.0.4.dist-info/WHEEL
invenio_oarepo_files_rest-1.0.4.dist-info/entry_points.txt
invenio_oarepo_files_rest-1.0.4.dist-info/top_level.txt
invenio_oarepo_files_rest-1.0.4.dist-info/RECORD
