Metadata-Version: 2.1
Name: invenio-oarepo-files-rest
Version: 1.0.4
Summary: REST API for uploading/downloading files for OArepo.
Home-page: https://github.com/oarepo/invenio-oarepo-files-rest
Author: Miroslav Bauer
Author-email: bauer@cesnet.cz
License: MIT
Keywords: invenio-oarepo-files-rest Invenio
Platform: any
Classifier: Environment :: Web Environment
Classifier: Intended Audience :: Developers
Classifier: License :: OSI Approved :: MIT License
Classifier: Operating System :: OS Independent
Classifier: Programming Language :: Python
Classifier: Topic :: Internet :: WWW/HTTP :: Dynamic Content
Classifier: Topic :: Software Development :: Libraries :: Python Modules
Classifier: Programming Language :: Python :: 2
Classifier: Programming Language :: Python :: 2.7
Classifier: Programming Language :: Python :: 3
Classifier: Programming Language :: Python :: 3.5
Classifier: Development Status :: 4 - Beta
Requires-Dist: Flask-BabelEx (>=0.9.3)
Requires-Dist: invenio[base,elasticsearch6,postgresql] (~=3.1.0)
Requires-Dist: arrow (>=0.12.1)
Requires-Dist: invenio-files-rest (==1.0.0a23)
